ikclient/__init__.py
ikclient/exceptions.py
ikclient/py.typed
ikclient/core/__init__.py
ikclient/core/client.py
ikclient/core/context.py
ikclient/core/io.py
ikclient/core/results.py
ikclient/core/workflow.py
ikclient/http/__init__.py
ikclient/http/auth.py
ikclient/http/exceptions.py
ikclient/http/logging.py
ikclient/http/session.py
ikclient/storage/__init__.py
ikclient/storage/client.py
ikclient/utils/__init__.py
ikclient/utils/image.py
ikomia_client-0.2.0.dist-info/METADATA
ikomia_client-0.2.0.dist-info/WHEEL
ikomia_client-0.2.0.dist-info/RECORD
