Metadata-Version: 2.4
Name: ikomia-client
Version: 0.2.0
Summary: Ikomia SCALE client library
Author-email: Ludovic Barusseau <ludovic.barusseau@ikomia.ai>, Loris Nezan <loris.nezan@ikomia.ai>
Classifier: Programming Language :: Python :: 3
Requires-Python: >=3.9
Requires-Dist: fsspec>=2025.3.2
Requires-Dist: httpx[http2]<1.0.0,>=0.27.0
Requires-Dist: numpy>=2.0.2
Requires-Dist: pillow<11.0.0,>=10.2.0
Requires-Dist: yarl<2.0.0,>=1.8.1
